mailck/__init__.py
mailck/main.py
mailck-0.4.0.dist-info/LICENSE
mailck-0.4.0.dist-info/METADATA
mailck-0.4.0.dist-info/WHEEL
mailck-0.4.0.dist-info/entry_points.txt
mailck-0.4.0.dist-info/RECORD
