Metadata-Version: 2.1
Name: mailck
Version: 0.4.0
Summary: a simple mail check utility, currently supporting IMAP
Home-page: https://gitlab.com/drad/mailck
License: GPL-3.0-only
Keywords: mail,imap,check,conky,cron,terminal,email
Author: drad
Author-email: sa@adercon.com
Maintainer: drad
Maintainer-email: sa@adercon.com
Requires-Python: >=3.11,<4.0
Classifier: License :: OSI Approved :: GNU General Public License v3 (GPLv3)
Classifier: Programming Language :: Python :: 3
Classifier: Programming Language :: Python :: 3.11
Classifier: Programming Language :: Python :: 3.12
Project-URL: Repository, https://gitlab.com/drad/mailck
